MANIFEST.in
README.txt
setup.py
authorid/__init__.py
authorid/authorid.py
authorid.egg-info/PKG-INFO
authorid.egg-info/SOURCES.txt
authorid.egg-info/dependency_links.txt
authorid.egg-info/entry_points.txt
authorid.egg-info/top_level.txt