Metadata-Version: 1.0
Name: authorid
Version: 0.0.1
Summary: A utility to determine the author of a document using linguistic analysis
Home-page: UNKNOWN
Author: Manan Shah
Author-email: manan.shah.777@gmail.com
License: MIT
Keywords: linguistics author finding
Platform: UNKNOWN
